autohandshake/__about__.py
autohandshake/__init__.py
autohandshake/chromedriver.exe
autohandshake/src/HandshakeBrowser.py
autohandshake/src/HandshakeSession.py
autohandshake/src/ViewAsStudent.py
autohandshake/src/__init__.py
autohandshake/src/constants.py
autohandshake/src/exceptions.py
autohandshake/src/file_download_utils.py
autohandshake/src/Pages/AccessRequestPage.py
autohandshake/src/Pages/AppointmentCalendarPage.py
autohandshake/src/Pages/CareerInterestsPage.py
autohandshake/src/Pages/EventPage.py
autohandshake/src/Pages/EventsPage.py
autohandshake/src/Pages/InsightsPage.py
autohandshake/src/Pages/InterviewSchedulePage.py
autohandshake/src/Pages/LoginPage.py
autohandshake/src/Pages/Page.py
autohandshake/src/Pages/StudentProfilePage.py
autohandshake/src/Pages/SurveyPage.py
autohandshake/src/Pages/WaitingRoomPage.py
autohandshake/src/Pages/__init__.py
autohandshake/src/Pages/SchoolSettings/AppointmentTypePage.py
autohandshake/src/Pages/SchoolSettings/AppointmentTypesListPage.py
autohandshake/src/Pages/SchoolSettings/LabelSettingsPage.py
autohandshake/src/Pages/SchoolSettings/MajorSettingsPage.py
autohandshake/src/Pages/SchoolSettings/StaffPage.py
autohandshake/src/Pages/SchoolSettings/__init__.py
autohandshake/tests/__init__.py
autohandshake/tests/account_specific_tests/__init__.py
autohandshake/tests/account_specific_tests/test_access_request_page.py
autohandshake/tests/account_specific_tests/test_appointment_calendar_page.py
autohandshake/tests/account_specific_tests/test_appointment_type_page.py
autohandshake/tests/account_specific_tests/test_appointment_types_list_page.py
autohandshake/tests/account_specific_tests/test_career_interests_page.py
autohandshake/tests/account_specific_tests/test_event_page.py
autohandshake/tests/account_specific_tests/test_events_page.py
autohandshake/tests/account_specific_tests/test_insights_page.py
autohandshake/tests/account_specific_tests/test_interview_schedule_page.py
autohandshake-1.4.8.dist-info/LICENSE
autohandshake-1.4.8.dist-info/METADATA
autohandshake-1.4.8.dist-info/WHEEL
autohandshake-1.4.8.dist-info/top_level.txt
autohandshake-1.4.8.dist-info/RECORD
