Metadata-Version: 2.1
Name: autohandshake
Version: 1.4.8
Summary: A library for automating tasks on the Handshake career services platform
Home-page: https://github.com/cedwards036/autohandshake
Author: Christopher Edwards
Author-email: cedwards036@gmail.com
License: MIT
Platform: UNKNOWN
Classifier: License :: OSI Approved :: MIT License
Classifier: Programming Language :: Python :: 3
Classifier: Programming Language :: Python :: 3.6
Requires-Dist: selenium
Requires-Dist: bs4
Requires-Dist: python-dateutil
Requires-Dist: keyring
